forsys/__init__.py
forsys/__main__.py
forsys/auxiliar.py
forsys/borders.py
forsys/cell.py
forsys/edge.py
forsys/exceptions.py
forsys/fmatrix.py
forsys/forsys.py
forsys/frames.py
forsys/general_matrix.py
forsys/myosin.py
forsys/plot.py
forsys/pmatrix.py
forsys/skeleton.py
forsys/stress_tensor.py
forsys/surface_evolver.py
forsys/tessellation.py
forsys/time_series.py
forsys/vertex.py
forsys/virtual_edges.py
forsys/wkt.py
forsys-1.1.1.dist-info/licenses/LICENSE
forsys-1.1.1.dist-info/METADATA
forsys-1.1.1.dist-info/WHEEL
forsys-1.1.1.dist-info/top_level.txt
forsys-1.1.1.dist-info/RECORD
