Metadata-Version: 2.4
Name: forsys
Version: 1.1.1
Summary: A tissue stress and cell pressure inference package with dynamical information
Author-email: Augusto Borges <borges.augustoar@gmail.com>
Project-URL: Homepage, https://github.com/borgesaugusto/forsys/
Keywords: systems biology,stress,pressure,inference
Classifier: Intended Audience :: Science/Research
Classifier: Intended Audience :: Education
Classifier: Programming Language :: Python
Classifier: Topic :: Scientific/Engineering :: Bio-Informatics
Classifier: Topic :: Scientific/Engineering :: Physics
Requires-Python: >=3.8
License-File: LICENSE
Requires-Dist: matplotlib>=3.6.0
Requires-Dist: numpy<2.0,>=1.23.0
Requires-Dist: opencv_python_headless>=4.5.0.0
Requires-Dist: pandas>=1.4.2
Requires-Dist: Pillow>=9.3.0
Requires-Dist: circle-fit>=0.2.1
Requires-Dist: scipy>=1.10.0
Requires-Dist: lmfit>=1.2.2
Requires-Dist: scikit-learn>=1.3.2
Requires-Dist: scikit-image<=0.21.0
Requires-Dist: tifffile>=2023.7.10
Requires-Dist: setuptools>=60.2.0
Requires-Dist: tomli; python_version < "3.11"
Provides-Extra: test
Requires-Dist: pytest>=7.2.0; extra == "test"
Requires-Dist: pytest-codspeed>=2.2.1; extra == "test"
Dynamic: license-file
